README.rst
setup.py
torch_tresnet/__init__.py
torch_tresnet/tresnet.py
torch_tresnet/utils.py
torch_tresnet.egg-info/PKG-INFO
torch_tresnet.egg-info/SOURCES.txt
torch_tresnet.egg-info/dependency_links.txt
torch_tresnet.egg-info/requires.txt
torch_tresnet.egg-info/top_level.txt
torch_tresnet/layers/__init__.py
torch_tresnet/layers/anti_aliasing.py
torch_tresnet/layers/avg_pool.py
torch_tresnet/layers/space_to_depth.py
torch_tresnet/layers/squeeze_and_excite.py