Metadata-Version: 1.0
Name: torch-tresnet
Version: 1.0.7
Summary: TResNet: High Performance GPU-Dedicated Architecture
Home-page: https://github.com/tczhangzhi/torch-tresnet
Author: ZHANG Zhi
Author-email: 850734033@qq.com
License: MIT
Platform: UNKNOWN
